nomad_catalysis/__init__.py
nomad_catalysis/apps/__init__.py
nomad_catalysis/apps/py_het_cat_app.py
nomad_catalysis/example_uploads/__init__.py
nomad_catalysis/example_uploads/het_catalysis_example/README.md
nomad_catalysis/example_uploads/het_catalysis_example/catalysis_sample.archive.json
nomad_catalysis/example_uploads/het_catalysis_example/methanol_synthesis.archive.json
nomad_catalysis/example_uploads/het_catalysis_example/methanol_synthesis_CuZnAl.xlsx
nomad_catalysis/example_uploads/het_catalysis_example/nomad.yaml
nomad_catalysis/example_uploads/template_example/README.md
nomad_catalysis/example_uploads/template_example/template_CatalysisCollection.xlsx
nomad_catalysis/parsers/__init__.py
nomad_catalysis/parsers/catalysis_parsers.py
nomad_catalysis/parsers/utils.py
nomad_catalysis/schema_packages/__init__.py
nomad_catalysis/schema_packages/catalysis.py
nomad_catalysis/schema_packages/chemical_data.py
nomad_catalysis-1.0.5.dist-info/licenses/LICENSE
nomad_catalysis-1.0.5.dist-info/METADATA
nomad_catalysis-1.0.5.dist-info/WHEEL
nomad_catalysis-1.0.5.dist-info/entry_points.txt
nomad_catalysis-1.0.5.dist-info/top_level.txt
nomad_catalysis-1.0.5.dist-info/RECORD
