Metadata-Version: 2.4
Name: nomad-catalysis
Version: 1.0.5
Summary: A NOMAD plugin for heterogeneous catalysis data.
Author: Julia Schumann, Hampus Näsström, Michael Götte
Author-email: fairmat@physik.hu-berlin.de
Maintainer-email: Julia Schumann <jschumann@physik.hu-berlin.de>, FAIRmat <fairmat@physik.hu-berlin.de>
License: 
Project-URL: Repository, https://github.com/FAIRmat-NFDI/nomad-catalysis-plugin
Classifier: Intended Audience :: Developers
Classifier: Operating System :: OS Independent
Classifier: Programming Language :: Python
Classifier: Programming Language :: Python :: 3.9
Classifier: Programming Language :: Python :: 3.10
Classifier: Programming Language :: Python :: 3.11
Classifier: Programming Language :: Python :: 3.12
Classifier: License :: OSI Approved :: MIT License
Requires-Python: >=3.10
License-File: LICENSE
Requires-Dist: nomad-lab[infrastructure]>=1.3.13
Requires-Dist: openpyxl
Provides-Extra: dev
Requires-Dist: ruff; extra == "dev"
Requires-Dist: pytest; extra == "dev"
Requires-Dist: structlog; extra == "dev"
Dynamic: license-file
